pywana/__init__.py
pywana/os.py
pywana/process.py
pywana/signal.py
pywana/snapper.py
pywana/systemd.py
pywana-2018.0.1.data/scripts/wana
pywana-2018.0.1.dist-info/LICENSE.txt
pywana-2018.0.1.dist-info/METADATA
pywana-2018.0.1.dist-info/WHEEL
pywana-2018.0.1.dist-info/top_level.txt
pywana-2018.0.1.dist-info/zip-safe
pywana-2018.0.1.dist-info/RECORD
