Metadata-Version: 2.1
Name: pywana
Version: 2018.0.1
Summary: Various system tools for Linux
Home-page: https://github.com/JM1/python-pywana
Author: Jakob Meng
Author-email: jakobmeng@web.de
Maintainer: Jakob Meng
Maintainer-email: jakobmeng@web.de
License: GPLv3+
Download-URL: https://github.com/JM1/python-pywana/archive/master.zip
Project-URL: Wiki, https://github.com/JM1/python-pywana/wiki
Project-URL: Issues, https://github.com/JM1/python-pywana/issues
Project-URL: Documentation, http://python-pywana.readthedocs.io/
Platform: Linux
Classifier: Development Status :: 4 - Beta
Classifier: Intended Audience :: Developers
Classifier: Intended Audience :: System Administrators
Classifier: License :: OSI Approved :: GNU General Public License v3 or later (GPLv3+)
Classifier: Operating System :: POSIX :: Linux
Classifier: Programming Language :: Python
Classifier: Programming Language :: Python :: 3
Classifier: Programming Language :: Python :: 3.5
Classifier: Programming Language :: Python :: 3.6
Classifier: Topic :: Software Development :: Libraries :: Python Modules
Classifier: Topic :: Utilities
Requires-Python: >=3.5
Requires-Dist: dbus-python
Requires-Dist: psutil
